{
  "list": {
    "SchoolNest": [
      "✓",
      "Id",
      "name",
      "numberOfSchools",
      "numberOfStudents",
      "Admins[0].email",
      "activeStudentsPercentage",
      "newTab"
    ],
    "School": [
      "✓",
      "Id",
      "name",
      "code",
      "city",
      "clientStatus",
      "numberOfSchoolClasses",
      "numberOfStudents",
      "Admins[0].email",
      "activeStudentsPercentage",
      "isFrozen",
      "newTab"
    ],
    "SchoolClass": [
      "✓",
      "Id",
      "name",
      "Escolas[0].name",
      "Redes[0].name",
      "schoolYear",
      "code",
      "clientStatus",
      "numberOfStudents",
      "Admins[0].email",
      "activeStudentsPercentage",
      "isFrozen",
      "newTab"
    ],
    "Student": [
      "✓",
      "Id",
      "name",
      "Turmas[0].name",
      "schoolYear",
      "email",
      "clientStatus",
      "points",
      "lastActivity.lastActivity",
      "newTab"
    ],
    "Professor": [
      "✓",
      "Id",
      "name",
      "email",
      "role",
      "school[0].school",
      "tasksCount",
      "assessmentsCount",
      "Disciplinas[0].name",
      "clientStatus",
      "newTab"
    ],
    "Parent": ["✓", "Id", "name", "email", "createdAt.createdAt", "newTab"],
    "Admin": [
      "✓",
      "Id",
      "name",
      "email",
      "role",
      "createdAt.createdAt",
      "newTab"
    ],
    "Task": [
      "✓",
      "Id",
      "name",
      "type",
      "createdAt.createdAt",
      "startDate.startDate",
      "endDate.endDate",
      "pointsMade",
      "schoolClass[0].name",
      "status",
      "creator.email",
      "creator.__typename",
      "creator.whatsappNumber",
      "isArchived",
      "newTab"
    ],
    "Assessment": [
      "✓",
      "Id",
      "name",
      "type",
      "startsAt.startsAt",
      "endsAt.endsAt",
      "knowledgeArea.knowledgeArea",
      "status",
      "schoolClass[0].name",
      "creator.email",
      "creator.__typename",
      "duration",
      "gradesReleased",
      "checkCheating",
      "shuffleQuestions",
      "powerUpsActive",
      "gradesReleased",
      "isArchived",
      "newTab"
    ]
  },

  "profile": {
    "SchoolNest": [
      "✓",
      "Id",
      "name",
      "numberOfSchools",
      "numberOfStudents",
      "activeStudentsPercentage",
      "Admins.admins",
      "newTab"
    ],
    "School": [
      "✓",
      "Id",
      "name",
      "Redes.schoolNest",
      "isFrozen",
      "code",
      "numberOfStudents",
      "activeStudentsPercentage",
      "admins.email",
      "newTab"
    ],
    "SchoolClass": [
      "✓",
      "Id",
      "name",
      "code",
      "schoolYear",
      "numberOfStudents",
      "activeStudentsPercentage",
      "isFrozen",
      "newTab"
    ],
    "Student": [
      "✓",
      "Id",
      "name",
      "Turmas[0].name",
      "email",
      "birthday.birthday",
      "lastActivity.lastActivity",
      "newTab"
    ],
    "Professor": [
      "✓",
      "Id",
      "name",
      "email",
      "role",
      "Turmas[0].name",
      "tasksCount",
      "assessmentsCount",
      "lastActivity.lastActivity",
      "Disciplinas[0].name",
      "newTab"
    ],
    "Parent": ["✓", "Id", "name", "email", "newTab"],
    "Admin": ["✓", "Id", "name", "email", "role", "newTab"],
    "Task": [
      "✓",
      "Id",
      "name",
      "type",
      "startDate.startDate",
      "endDate.endDate",
      "pointsMade",
      "schoolClass[0].name",
      "status",
      "creator.email",
      "creator.__typename",
      "isArchived",
      "newTab"
    ],
    "Assessment": [
      "✓",
      "Id",
      "name",
      "type",
      "startsAt.startsAt",
      "endsAt.endsAt",
      "knowledgeArea.knowledgeArea",
      "status",
      "schoolClass[0].name",
      "creator.email",
      "creator.__typename",
      "duration",
      "gradesReleased",
      "checkCheating",
      "shuffleQuestions",
      "powerUpsActive",
      "gradesReleased",
      "isArchived",
      "newTab"
    ],
    "Course": ["✓", "Id", "name", "knowledgeArea.name"],
    "QuestionsAnswered": [
      "✓",
      "newTab",
      "Id",
      "fraction",
      "points",
      "bonusPoints",
      "topic.topic.course.name",
      "topic.topic.topic"
    ],
    "AssessmentStudent": [
      "Assessment.Id",
      "Assessment.name",
      "Assessment.type",
      "attempts",
      "grade",
      "timeSpent",
      "Assessment.creator.email",
      "Assessment.creator.__typename",
      "status"
    ],
    "AssignedContext": [
      "✓",
      "Id",
      "student.email",
      "student.name",
      "context.name",
      "context.knowledgeArea.name",
      "type",
      "context.Id",
      "student.powerUpsInContext",
      "student.powerUpsCount",
      "student.questionsAnsweredCountInContext",
      "grade",
      "timeSpent",
      "status",
      "newTab"
    ],
    "Ranking": [
      "✓",
      "position",
      "name",
      "email",
      "belongsTo",
      "schoolYear",
      "points"
    ],
    "Topic": [
      "✓",
      "name",
      "course.name",
      "course.knowledgeArea.name",
      "questionsCountVisible"
    ],
    "KnowledgeArea": ["✓", "Id", "name"],
    "AssessmentQuestion": [
      "Id",
      "order",
      "maxGrade",
      "Question.topic.course.name",
      "Question.topic.name",
      "Question.name",
      "view"
    ],
    "_StudentPhases": [
      "createdAt.phase",
      "Phase.order",
      "Phase.level.name",
      "Phase.level.planet.name",
      "stars"
    ],
    "_StudentMissions": [
      "createdAt.formatted",
      "Mission.title",
      "Mission.description",
      "completed",
      "completedAt.formatted"
    ],
    "PointTransaction": [
      "studentAnswer.createdAt.receivedAt",
      "studentAnswer.fraction",
      "studentAnswer.question.topic.course.name",
      "studentAnswer.question.topic.name",
      "studentAnswer.assignedContext.context.__typename",
      "studentAnswer.assignedContext.context.type",
      "studentAnswer.assignedContext.context.name",
      "studentAnswer.assignedContext.context.Id",
      "quantity",
      "bonus",
      "studentAnswer.powerUpUsed.name",
      "view"
    ],
    "StudentAnswer": [
      "createdAt.receivedAt",
      "fraction",
      "question.topic.course.name",
      "question.topic.name",
      "assignedContext.context.__typename",
      "assignedContext.context.type",
      "assignedContext.context.name",
      "assignedContext.context.Id",
      "points",
      "bonusPoints",
      "powerUpUsed.name",
      "view"
    ],
    "KeyTransaction": ["createdAt.formatted", "quantity"],
    "ChestTransaction": [
      "createdAt.receivedAt",
      "quantity",
      "chest.name",
      "chest.keysRequired"
    ],
    "TrophyTransaction": ["createdAt.formatted", "battle.type", "quantity"],
    "Item": ["name", "type", "rarity", "level.name"]
  },
  "nationalOlympics": {
    "Ranking Alunos": [
      "position",
      "name",
      "email",
      "schoolYear",
      "belongsTo",
      "points"
    ],
    "Ranking Turmas": [
      "position",
      "name",
      "points",
      "schoolYear",
      "pointsAverage"
    ],
    "Ranking Escolas": ["position", "name", "points", "pointsAverage"],
    "Alunos": [
      "Id",
      "name",
      "email",
      "schoolClasses.name",
      "schoolClasses.school.name",
      "completedNationalOlympicsMissionsCount",
      "correctQuestionsAnsweredPercentageInContext"
    ],
    "Turmas": [
      "Id",
      "name",
      "school.name",
      "numberOfStudents",
      "completedNationalOlympicsMissionsCountAverage",
      "activeStudentsPercentage"
    ],
    "Escolas": [
      "Id",
      "name",
      "numberOfSchoolClasses",
      "numberOfStudents",
      "completedNationalOlympicsMissionsCountAverage",
      "activeStudentsPercentage"
    ]
  }
}
